<annotation>
	<folder>camera</folder>
	<filename>IMG_1409.JPG</filename>
	<path>C:\tensorflow1\source\camera\IMG_1409.JPG</path>
	<source>
		<database>Unknown</database>
	</source>
	<size>
		<width>189</width>
		<height>252</height>
		<depth>3</depth>
	</size>
	<segmented>0</segmented>
	<object>
		<name>paper_white</name>
		<pose>Unspecified</pose>
		<truncated>0</truncated>
		<difficult>0</difficult>
		<bndbox>
			<xmin>43</xmin>
			<ymin>62</ymin>
			<xmax>155</xmax>
			<ymax>149</ymax>
		</bndbox>
	</object>
</annotation>
